cellenics_api/__init__.py
cellenics_api/cognito.config.json
cellenics_api/connection.py
cellenics_api/default.config.json
cellenics_api/sample.py
cellenics_api/sample_file.py
cellenics_api/utils.py
cellenics_api-0.0.4.dist-info/LICENSE
cellenics_api-0.0.4.dist-info/METADATA
cellenics_api-0.0.4.dist-info/WHEEL
cellenics_api-0.0.4.dist-info/top_level.txt
cellenics_api-0.0.4.dist-info/RECORD
