Metadata-Version: 2.1
Name: cellenics-api
Version: 0.0.4
Summary: For programmatic upload of files to Cellencis
Home-page: https://github.com/Kristian-A/cellenics-api
Author: Kristian Apostolov
Author-email: kristian@biomage.net
Classifier: Programming Language :: Python :: 3
Classifier: License :: OSI Approved :: MIT License
Classifier: Operating System :: OS Independent
Requires-Python: >=3.7
License-File: LICENSE
